paoding/__init__.py
paoding/analysis.py
paoding/argument_parser.py
paoding/evaluate.py
paoding/nn_utils.py
paoding/train.py
paoding/utils.py
PaoDing-0.1.1.dist-info/LICENSE
PaoDing-0.1.1.dist-info/METADATA
PaoDing-0.1.1.dist-info/WHEEL
PaoDing-0.1.1.dist-info/top_level.txt
PaoDing-0.1.1.dist-info/RECORD
