Metadata-Version: 2.1
Name: PaoDing
Version: 0.1.1
Summary: An NLP-oriented PyTorch wrapper that makes your life easier.
Author: Zhaofeng Wu
Author-email: zfw7@cs.washington.edu
License: Apache 2.0
Keywords: pytorch deep learning machine NLP AI
Classifier: Intended Audience :: Science/Research
Classifier: Development Status :: 2 - Pre-Alpha
Classifier: License :: OSI Approved :: Apache Software License
Classifier: Programming Language :: Python :: 3
Classifier: Topic :: Scientific/Engineering :: Artificial Intelligence
Requires-Python: >=3.9.0
License-File: LICENSE
Requires-Dist: allennlp (==2.8.0)
Requires-Dist: datasets (==1.12.1)
Requires-Dist: dill (==0.3.4)
Requires-Dist: multiprocess (==0.70.12.2)
Requires-Dist: numpy (==1.21.2)
Requires-Dist: pytorch-lightning (==1.4.8)
Requires-Dist: scikit-learn
Requires-Dist: seaborn (==0.11.2)
Requires-Dist: setuptools (==59.5.0)
Requires-Dist: tokenizers (==0.10.3)
Requires-Dist: torch (==1.9.1)
Requires-Dist: torchmetrics (==0.5.1)
Requires-Dist: tqdm (==4.62.2)
Requires-Dist: transformers (==4.10.3)
